Metadata-Version: 2.1
Name: ont-tombo
Version: 1.5.1
Summary: Analysis of raw nanopore sequencing data.
Home-page: https://github.com/nanoporetech/tombo
Author: Marcus Stoiber
Author-email: marcus.stoiber@nanoporetech.com
License: mpl-2.0
Keywords: nanopore high-throughput sequencing correction genome
Platform: UNKNOWN
Classifier: Development Status :: 5 - Production/Stable
Classifier: Intended Audience :: Science/Research
Classifier: Natural Language :: English
Classifier: License :: OSI Approved :: Mozilla Public License 2.0 (MPL 2.0)
Classifier: Programming Language :: Python
Classifier: Programming Language :: Python :: 2
Classifier: Programming Language :: Python :: 2.7
Classifier: Programming Language :: Python :: 3
Classifier: Programming Language :: Python :: 3.4
Classifier: Programming Language :: Python :: 3.5
Classifier: Programming Language :: Python :: 3.6
Classifier: Topic :: Scientific/Engineering :: Bio-Informatics
Requires-Dist: h5py
Requires-Dist: numpy
Requires-Dist: scipy
Requires-Dist: cython
Requires-Dist: setuptools (>=18.0)
Requires-Dist: mappy (>=2.10)
Requires-Dist: future
Requires-Dist: tqdm
Provides-Extra: full
Requires-Dist: pyfaidx ; extra == 'full'
Requires-Dist: rpy2 (<=2.9.5) ; extra == 'full'
